cerver/__init__.py
cerver/cerver.py
cerver/files.py
cerver/handler.py
cerver/lib.py
cerver/network.py
cerver/packets.py
cerver/timer.py
cerver/version.py
cerver/http/__init__.py
cerver/http/alg.py
cerver/http/content.py
cerver/http/headers.py
cerver/http/http.py
cerver/http/multipart.py
cerver/http/origin.py
cerver/http/query.py
cerver/http/redirect.py
cerver/http/request.py
cerver/http/response.py
cerver/http/route.py
cerver/http/status.py
cerver/http/validation.py
cerver/threads/__init__.py
cerver/threads/bsem.py
cerver/threads/job.py
cerver/threads/threads.py
cerver/threads/worker.py
cerver/types/__init__.py
cerver/types/string.py
cerver/utils/__init__.py
cerver/utils/log.py
cerver/utils/utils.py
pycerver-0.9.8.dist-info/licenses/LICENSE
pycerver-0.9.8.dist-info/METADATA
pycerver-0.9.8.dist-info/WHEEL
pycerver-0.9.8.dist-info/top_level.txt
pycerver-0.9.8.dist-info/RECORD
