Metadata-Version: 2.4
Name: pycerver
Version: 0.9.8
Summary: PyCerver is a pure Python wrapper around the cerver framework
Home-page: https://github.com/ermiry-com/py-cerver
Author: Erick Salas
Author-email: erick.salas@ermiry.com
Project-URL: Bug Tracker, https://github.com/ermiry-com/py-cerver/issues
Classifier: Programming Language :: Python :: 3
Classifier: License :: OSI Approved :: MIT License
Classifier: Operating System :: OS Independent
Requires-Python: >=3.6
License-File: LICENSE
Dynamic: license-file
